{"OrderNumber":"ECI2019072914471355115910","Result":{"PermissionInfo":[],"Penalty":[],"Exceptions":[{"AddReason":"未依照《企业信息公示暂行条例》第八条规定的期限公示2015年度年度报告的","AddDate":"2016-07-04","RomoveReason":"","RemoveDate":"","DecisionOffice":"蒙自市市场监督管理局","RemoveDecisionOffice":null}],"ShiXinItems":[],"ZhiXingItems":[],"MPledge":[],"Liquidation":null,"Pledge":[],"SpotCheck":[],"CompanyTaxCreditItems":[],"CompanyProducts":[],"PermissionEciInfo":[],"PenaltyCreditChina":[],"Partners":[],"Employees":[],"Branches":[],"ChangeRecords":[],"ContactInfo":{"WebSite":null,"PhoneNumber":"15924628130","Email":null},"Industry":{"IndustryCode":"J","Industry":"金融业","SubIndustryCode":"68","SubIndustry":"保险业","MiddleCategoryCode":"689","MiddleCategory":"其他保险活动","SmallCategoryCode":"6890","SmallCategory":"其他保险活动"},"Area":{"Province":"云南省","City":"红河哈尼族彝族自治州","County":"蒙自市"},"InsuredCount":null,"EnglishName":null,"PersonScope":"","KeyNo":"12f65ea690c1ff03d5e6fff7297eaeb7","Name":"华泰保险销售有限公司云南省分公司蒙自市保丰营业部","No":"532522000007897","BelongOrg":"蒙自市市场监督管理局","OperName":"李彬","StartDate":"2012-08-31 00:00:00","EndDate":"","Status":"注销","Province":"YN","UpdatedDate":"2019-07-26 11:11:34","CreditCode":"","RegistCapi":"","EconKind":"有限责任公司分公司（非自然人投资或控股的法人独资）","Address":"蒙自市银河路7号","Scope":"在云南省行政辖区内代理销售保险产品;代理收取保费;代理相关保险业务的损失勘查和理赔;中国保监会批准的其他业务。","TermStart":"2012-08-31 00:00:00","TeamEnd":"","CheckDate":"2013-06-05 00:00:00","OrgNo":null,"IsOnStock":"0","StockNumber":null,"StockType":null,"OriginalName":[{"Name":"华泰保险销售(上海)有限公司云南省分公司蒙自市保丰营业部","ChangeDate":""}],"ImageUrl":"https://co-image.qichacha.com/CompanyImage/12f65ea690c1ff03d5e6fff7297eaeb7.jpg?x-oss-process=image/resize,w_160","EntType":"0","RecCap":null},"Status":"200","Message":"查询成功"}