{"OrderNumber":"ECI2019072914532646591440","Result":{"PermissionInfo":[{"Name":"","Province":"云南","Liandate":"2016-04-13","CaseNo":""},{"Name":"","Province":"云南","Liandate":"2016-04-13","CaseNo":""}],"Penalty":[],"Exceptions":[],"ShiXinItems":[],"ZhiXingItems":[{"Id":"796e9be695c611a878bfc621920b27281","Sourceid":"0","Name":"天安财产保险股份有限公司曲靖中心支公司罗平营销服务部","Liandate":"2019-07-22","Anno":"(2019)云0324执1145号","ExecuteGov":"罗平县人民法院","Biaodi":"13000","Status":"","PartyCardNum":"91530324797****4740","Updatedate":null}],"MPledge":[],"Liquidation":null,"Pledge":[],"SpotCheck":[],"CompanyTaxCreditItems":[],"CompanyProducts":[],"PermissionEciInfo":[],"PenaltyCreditChina":[],"Partners":[],"Employees":[],"Branches":[],"ChangeRecords":[{"ProjectName":"负责人变更","BeforeContent":"吴明荣","AfterContent":"冯雄娟*","ChangeDate":"2018-07-05"},{"ProjectName":"联络员备案","BeforeContent":"粱秋霞 *** 备案手机:******","AfterContent":"吕红 *** 备案手机:****** (网上办理)","ChangeDate":"2016-05-11"},{"ProjectName":"其他事项备案","BeforeContent":"0.0000","AfterContent":"","ChangeDate":"2014-06-30"},{"ProjectName":"地址变更（住所地址、经营场所、驻在地址等变更）","BeforeContent":"罗平县罗雄镇云贵路烟草小区\n电话:******\n邮编:655800","AfterContent":"云南省曲靖市罗平县罗雄镇云贵路烟草小区\n电话:******\n邮编:655800","ChangeDate":"2014-06-30"},{"ProjectName":"其他事项备案","BeforeContent":"姓名:钱昆\n性别:男  \n住所：****","AfterContent":"姓名:吴明荣\n性别:男  \n住所：****","ChangeDate":"2014-06-30"},{"ProjectName":"法定代表人(负责人、董事长、首席代表)变更","BeforeContent":"姓名:钱昆\n性别:男  \n住所：****","AfterContent":"姓名:吴明荣\n性别:男  \n住所：****","ChangeDate":"2014-06-30"}],"ContactInfo":{"WebSite":[{"Name":null,"Url":"http://17700560.1024sj.com/"}],"PhoneNumber":"0874-8210111","Email":"kmqj07@tianan-insurance.com"},"Industry":{"IndustryCode":"J","Industry":"金融业","SubIndustryCode":"68","SubIndustry":"保险业","MiddleCategoryCode":"681","MiddleCategory":"人身保险","SmallCategoryCode":"6811","SmallCategory":"人寿保险"},"Area":{"Province":"云南省","City":"曲靖市","County":"罗平县"},"InsuredCount":"3","EnglishName":null,"PersonScope":"","KeyNo":"acf9f9433155e1e97a36d55f6ad5f3cc","Name":"天安财产保险股份有限公司曲靖中心支公司罗平营销服务部","No":"530324000002405","BelongOrg":"罗平县市场监督管理局","OperName":"冯雄娟","StartDate":"2006-11-22 00:00:00","EndDate":"","Status":"存续（在营、开业、在册）","Province":"YN","UpdatedDate":"2019-07-19 11:39:52","CreditCode":"915303247972284740","RegistCapi":"","EconKind":"股份有限公司分公司(非上市、国有控股)","Address":"云南省曲靖市罗平县罗雄镇云贵路烟草小区","Scope":"按中国保险监督管理委员会批准的业务范围经营***","TermStart":"2009-08-04 00:00:00","TeamEnd":"","CheckDate":"2018-07-05 00:00:00","OrgNo":"79722847-4","IsOnStock":"0","StockNumber":null,"StockType":null,"OriginalName":[{"Name":"天安保险股份有限公司曲靖中心支公司罗平营销服务部","ChangeDate":""}],"ImageUrl":"https://co-image.qichacha.com/CompanyImage/acf9f9433155e1e97a36d55f6ad5f3cc.jpg?x-oss-process=image/resize,w_160","EntType":"0","RecCap":null},"Status":"200","Message":"查询成功"}