{"OrderNumber":"ECI2019072914393764932078","Result":{"PermissionInfo":[{"Name":"","Province":"上海","Liandate":"2018-10-26","CaseNo":"沪银保监(筹)复11号"},{"Name":"","Province":"上海","Liandate":"2018-10-11","CaseNo":"沪保监许可[2018]316号"},{"Name":"","Province":"上海","Liandate":"2018-08-01","CaseNo":"沪保监许可[2018]247号"},{"Name":"","Province":"上海","Liandate":"2018-07-31","CaseNo":"沪保监许可[2018]245号"},{"Name":"","Province":"上海","Liandate":"2018-07-23","CaseNo":"沪保监许可[2018]232号"},{"Name":"","Province":"上海","Liandate":"2018-07-13","CaseNo":"pdy08105931010612d4001"},{"Name":"","Province":"上海","Liandate":"2018-07-13","CaseNo":"pdy08105931010612d4001"},{"Name":"","Province":"上海","Liandate":"2018-07-12","CaseNo":"沪保监许可[2018]221号"},{"Name":"","Province":"上海","Liandate":"2018-04-03","CaseNo":"沪保监许可[2018]96号"},{"Name":"","Province":"上海","Liandate":"2018-03-16","CaseNo":"沪保监许可[2018]80号"},{"Name":"","Province":"上海","Liandate":"2018-03-12","CaseNo":"沪保监许可[2018]73号"},{"Name":"","Province":"上海","Liandate":"2018-02-07","CaseNo":"沪保监许可[2018]43号"},{"Name":"","Province":"上海","Liandate":"2018-01-23","CaseNo":"沪保监许可[2018]31号"},{"Name":"","Province":"上海","Liandate":"2018-01-15","CaseNo":"沪保监许可[2018]22号"},{"Name":"","Province":"上海","Liandate":"2017-12-16","CaseNo":"沪保监许可[2017]345号"},{"Name":"","Province":"上海","Liandate":"2017-11-03","CaseNo":"沪保监许可[2017]295号"},{"Name":"","Province":"上海","Liandate":"2017-10-10","CaseNo":"沪保监许可[2017]266号"},{"Name":"","Province":"上海","Liandate":"2017-07-28","CaseNo":"nf0149310106926201"},{"Name":"","Province":"上海","Liandate":"2017-06-09","CaseNo":"沪保监许可[2017]141号"},{"Name":"","Province":"上海","Liandate":"2017-05-19","CaseNo":"沪保监许可[2017]119号"},{"Name":"","Province":"上海","Liandate":"2017-05-09","CaseNo":"沪保监许可[2017]110号"},{"Name":"","Province":"上海","Liandate":"2017-04-14","CaseNo":"沪保监许可[2017]86号"},{"Name":"","Province":"上海","Liandate":"2017-03-29","CaseNo":"D35437310106610113"},{"Name":"","Province":"上海","Liandate":"2016-08-24","CaseNo":""},{"Name":"","Province":"上海","Liandate":"2016-08-24","CaseNo":""}],"Penalty":[{"DocNo":"231010120170000190","PenaltyType":"其他违法","OfficeName":"上海市税务稽查一局","Content":"稽查检查税务处理税款31153.6元及罚款15000元","PenaltyDate":"2017-09-22","PublicDate":"2017-09-22","Remark":null},{"DocNo":"","PenaltyType":"对违反《中华人民共和国消防法》行为的处罚","OfficeName":"徐汇区公安消防支队","Content":"","PenaltyDate":"2015-02-03","PublicDate":"2015-02-03","Remark":null}],"Exceptions":[],"ShiXinItems":[],"ZhiXingItems":[],"MPledge":[],"Liquidation":null,"Pledge":[],"SpotCheck":[],"CompanyTaxCreditItems":[{"No":"9131000083434562XE","Name":"中国平安人寿保险股份有限公司上海分公司","Year":"2018","Level":"A"},{"No":"9131000083434562XE","Name":"中国平安人寿保险股份有限公司上海分公司","Year":"2017","Level":"A"},{"No":"9131000083434562XE","Name":"中国平安人寿保险股份有限公司上海分公司","Year":"2016","Level":"A"}],"CompanyProducts":[],"PermissionEciInfo":[{"LicensDocNo":"沪杨公消验字〔2014〕第0089号","LicensDocName":"建设工程竣工消防验收","ValidityFrom":"","ValidityTo":"","LicensOffice":"上海市杨浦区公安消防支队","LicensContent":""},{"LicensDocNo":"NF0149310106926201","LicensDocName":"医疗机构执业登记","ValidityFrom":"2015-07-01","ValidityTo":"2020-06-30","LicensOffice":"静安区卫生和计划生育委员会","LicensContent":"内科 /医学检验科;临床体液、血液专业;临床化学检验专业 /医学影像科;超声诊断专业 /中医科"}],"PenaltyCreditChina":[{"CaseNo":"沪地税一稽罚〔2017〕26号","Name":"中国平安人寿保险股份有限公司上海分公司案件","Liandate":"2017-09-22","Province":"CN","OwnerName":"中国平安人寿保险股份有限公司上海分公司","CaseReason":"该公司2013年3月12日购买购物卡75,000.00元，2013年6月27日购买购物卡75,000.00元，已全部发放给个人客户，未代扣代缴个人所得税。"}],"Partners":[],"Employees":[],"Branches":[],"ChangeRecords":[{"ProjectName":"经营范围变更","BeforeContent":"承保人民币和外币的各种人身保险业务,包括各类人寿保险、健康保险(不包括“团体长期健康保险”)、意外伤害保险等保险业务；办理各种法定人身保险业务；代理国内外保险机构检验、理赔、及其委托的其他有关事宜；经中国保监会批准的其他业务。\n【依法须经批准的项目,经相关部门批准后方可开展经营活动】","AfterContent":"承保人民币和外币的各种人身保险业务,包括各类人寿保险、健康保险(不包括“团体长期健康保险”)、意外伤害保险等保险业务；办理各种法定人身保险业务；代理国内外保险机构检验、理赔、及其委托的其他有关事宜；证券投资基金销售业务；经中国保监会批准的其他业务。\n【依法须经批准的项目,经相关部门批准后方可开展经营活动】","ChangeDate":"2015-07-09"}],"ContactInfo":{"WebSite":null,"PhoneNumber":"021-62078931","Email":"linhua2@pingan.com.cn"},"Industry":{"IndustryCode":"J","Industry":"金融业","SubIndustryCode":"68","SubIndustry":"保险业","MiddleCategoryCode":"681","MiddleCategory":"人身保险","SmallCategoryCode":"6811","SmallCategory":"人寿保险"},"Area":{"Province":"上海市","City":"上海市","County":""},"InsuredCount":"1050","EnglishName":"Ping An Insurance (Group) Company of China, Ltd.","PersonScope":"500-999人","KeyNo":"be8cfa3aa3f6dc5dc3cf1618f692fd5b","Name":"中国平安人寿保险股份有限公司上海分公司","No":"310000000063285","BelongOrg":"上海市工商局","OperName":"韩光","StartDate":"1998-06-29 00:00:00","EndDate":"","Status":"存续（在营、开业、在册）","Province":"SH","UpdatedDate":"2019-07-19 23:57:52","CreditCode":"9131000083434562XE","RegistCapi":"","EconKind":"其他股份有限公司分公司(非上市)","Address":"上海市常熟路8号","Scope":"承保人民币和外币的各种人身保险业务,包括各类人寿保险、健康保险(不包括“团体长期健康保险”)、意外伤害保险等保险业务;办理各种法定人身保险业务;代理国内外保险机构检验、理赔、及其委托的其他有关事宜;证券投资基金销售业务;经中国保监会批准的其他业务。【依法须经批准的项目,经相关部门批准后方可开展经营活动】","TermStart":"1998-06-29 00:00:00","TeamEnd":"","CheckDate":"1998-06-29 00:00:00","OrgNo":"83434562-X","IsOnStock":"0","StockNumber":null,"StockType":null,"OriginalName":[{"Name":"中国平安保险股份有限公司上海分公司人身险营业部","ChangeDate":""}],"ImageUrl":"https://co-image.qichacha.com/CompanyImage/be8cfa3aa3f6dc5dc3cf1618f692fd5b.jpg?x-oss-process=image/resize,w_160","EntType":"0","RecCap":null},"Status":"200","Message":"查询成功"}