{"OrderNumber":"ECI2019072914402476045607","Result":{"PermissionInfo":[],"Penalty":[],"Exceptions":[],"ShiXinItems":[],"ZhiXingItems":[],"MPledge":[],"Liquidation":null,"Pledge":[],"SpotCheck":[],"CompanyTaxCreditItems":[],"CompanyProducts":[],"PermissionEciInfo":[],"PenaltyCreditChina":[],"Partners":[],"Employees":[],"Branches":[],"ChangeRecords":[{"ProjectName":"经营场所变更","BeforeContent":"中国(上海)自由贸易试验区灵山路898、958号1号楼二层整层、一层101室","AfterContent":"中国(上海)自由贸易试验区灵山路898、958号1号楼二层整层、一层101室、102室","ChangeDate":"2018-08-21"},{"ProjectName":"名称变更","BeforeContent":"中国平安人寿保险股份有限公司上海分公司浦东浦建路营销服务部","AfterContent":"中国平安人寿保险股份有限公司上海浦东灵山路营销服务部","ChangeDate":"2017-08-03"},{"ProjectName":"经营场所变更","BeforeContent":"中国(上海)自由贸易试验区浦建路145号3楼","AfterContent":"中国(上海)自由贸易试验区灵山路898、958号1号楼二层整层、一层101室","ChangeDate":"2017-08-03"},{"ProjectName":"负责人变更","BeforeContent":"蒋士华","AfterContent":"刘景观*","ChangeDate":"2017-08-03"}],"ContactInfo":{"WebSite":null,"PhoneNumber":"021-62078931","Email":"linhua2@pingan.com.cn"},"Industry":{"IndustryCode":"J","Industry":"金融业","SubIndustryCode":"68","SubIndustry":"保险业","MiddleCategoryCode":"689","MiddleCategory":"其他保险活动","SmallCategoryCode":"6890","SmallCategory":"其他保险活动"},"Area":{"Province":"上海市","City":"上海市","County":""},"InsuredCount":"1050","EnglishName":null,"PersonScope":"10000人以上","KeyNo":"b276b5292303a182d23bf5fd529b3f1b","Name":"中国平安人寿保险股份有限公司上海浦东灵山路营销服务部","No":"310115000839160","BelongOrg":"自由贸易试验区市场监管局","OperName":"刘景观","StartDate":"2004-06-11 00:00:00","EndDate":"","Status":"存续（在营、开业、在册）","Province":"SH","UpdatedDate":"2019-07-19 13:45:17","CreditCode":"913101157927969073","RegistCapi":"","EconKind":"其他股份有限公司分公司(非上市)","Address":"中国(上海)自由贸易试验区灵山路898、958号1号楼二层整层、一层101室、102室","Scope":"对营销员开展培训及日常管理,收取营销员代收的保险费、投保单等单证,分发保险公司签发的保险单、保险收据等相关单证,接受客户的咨询、投诉。【依法须经批准的项目,经相关部门批准后方可开展经营活动】","TermStart":"2004-06-11 00:00:00","TeamEnd":"","CheckDate":"2004-06-11 00:00:00","OrgNo":"79279690-7","IsOnStock":"0","StockNumber":null,"StockType":null,"OriginalName":[{"Name":"中国平安人寿保险股份有限公司上海分公司浦东浦建路营销服务部","ChangeDate":"2017-08-03"}],"ImageUrl":"https://co-image.qichacha.com/CompanyImage/b276b5292303a182d23bf5fd529b3f1b.jpg?x-oss-process=image/resize,w_160","EntType":"0","RecCap":null},"Status":"200","Message":"查询成功"}