{"OrderNumber":"ECI2019072914415751982375","Result":{"PermissionInfo":[],"Penalty":[],"Exceptions":[],"ShiXinItems":[],"ZhiXingItems":[],"MPledge":[],"Liquidation":null,"Pledge":[],"SpotCheck":[],"CompanyTaxCreditItems":[{"No":"913101145529753753","Name":"上海德雅保险代理有限公司","Year":"2018","Level":"A"}],"CompanyProducts":[],"PermissionEciInfo":[],"PenaltyCreditChina":[],"Partners":[{"StockName":"严烈章","StockType":"自然人股东","StockPercent":"35.00%","ShouldCapi":"70","ShoudDate":"2010-04-08","InvestType":"货币","InvestName":"货币","RealCapi":"40","CapiDate":"2009-12-03"},{"StockName":"黄国华","StockType":"自然人股东","StockPercent":"25.00%","ShouldCapi":"50","ShoudDate":"2010-04-08","InvestType":"货币","InvestName":"货币","RealCapi":"40","CapiDate":"2009-12-07"},{"StockName":"徐海根","StockType":"自然人股东","StockPercent":"10.00%","ShouldCapi":"20","ShoudDate":"2010-04-08","InvestType":"货币","InvestName":"货币","RealCapi":"20","CapiDate":"2011-09-28"},{"StockName":"刘莉","StockType":"自然人股东","StockPercent":"10.00%","ShouldCapi":"20","ShoudDate":"2010-04-08","InvestType":"货币","InvestName":"货币","RealCapi":"20","CapiDate":"2009-12-07"},{"StockName":"张有礼","StockType":"自然人股东","StockPercent":"10.00%","ShouldCapi":"20","ShoudDate":"2010-04-08","InvestType":"货币","InvestName":"货币","RealCapi":"20","CapiDate":"2009-12-07"},{"StockName":"黄建荣","StockType":"自然人股东","StockPercent":"5.00%","ShouldCapi":"10","ShoudDate":"2010-04-08","InvestType":"货币","InvestName":"货币","RealCapi":"10","CapiDate":"2011-09-28"},{"StockName":"毕耀亭","StockType":"自然人股东","StockPercent":"5.00%","ShouldCapi":"10","ShoudDate":"2010-04-08","InvestType":"货币","InvestName":"货币","RealCapi":"10","CapiDate":"2011-09-28"}],"Employees":[{"Name":"张有礼","Job":"监事"},{"Name":"黄国华","Job":"执行董事"}],"Branches":[],"ChangeRecords":[{"ProjectName":"住所变更","BeforeContent":"上海市嘉定区众仁路399号1幢401-2室","AfterContent":"上海市徐汇区中山西路2025号1406室","ChangeDate":"2017-03-08"},{"ProjectName":"章程修正案备案","BeforeContent":"无","AfterContent":"2017-02-16章程修正案","ChangeDate":"2017-03-08"},{"ProjectName":"一般经营项目变更","BeforeContent":"代理销售保险产品,代理收取保险费,代理相关保险业务的损失勘查和理赔,中国保监会规定的其他业务","AfterContent":"保险专业代理。","ChangeDate":"2015-11-24"},{"ProjectName":"投资人(股权)变更","BeforeContent":"毕耀亭；黄建荣；刘莉；张有礼；黄国华*；徐海根；严烈章；徐立峰【退出】","AfterContent":"张有礼；毕耀亭；徐海根；黄建荣；严烈章；刘莉；黄国华*","ChangeDate":"2015-11-24"},{"ProjectName":"法定代表人变更","BeforeContent":"徐立峰","AfterContent":"黄国华*","ChangeDate":"2015-11-24"},{"ProjectName":"住所变更","BeforeContent":"上海市嘉定区南翔镇沪宜公路355号1幢108室","AfterContent":"上海市嘉定区众仁路399号1幢401-2室","ChangeDate":"2015-11-24"},{"ProjectName":"董事备案","BeforeContent":"徐立峰【退出】","AfterContent":"黄国华*【新增】","ChangeDate":"2015-11-24"}],"ContactInfo":{"WebSite":null,"PhoneNumber":"021-62581820","Email":"gaohai_001@hotmail.com"},"Industry":{"IndustryCode":"J","Industry":"金融业","SubIndustryCode":"68","SubIndustry":"保险业","MiddleCategoryCode":"685","MiddleCategory":"保险中介服务","SmallCategoryCode":null,"SmallCategory":null},"Area":{"Province":"上海市","City":"上海市","County":"徐汇区"},"InsuredCount":"4","EnglishName":null,"PersonScope":"","KeyNo":"b402dbcccece51ea9124f8dbc5056761","Name":"上海德雅保险代理有限公司","No":"310114002104984","BelongOrg":"徐汇区市场监督管理局","OperName":"黄国华","StartDate":"2010-04-08 00:00:00","EndDate":"","Status":"存续（在营、开业、在册）","Province":"SH","UpdatedDate":"2019-07-10 00:03:16","CreditCode":"913101145529753753","RegistCapi":"200万元人民币","EconKind":"有限责任公司(自然人投资或控股)","Address":"上海市徐汇区中山西路2025号1406室","Scope":"保险专业代理。【依法须经批准的项目,经相关部门批准后方可开展经营活动】","TermStart":"2010-04-08 00:00:00","TeamEnd":"2020-04-07 00:00:00","CheckDate":"2010-04-08 00:00:00","OrgNo":"55297537-5","IsOnStock":"0","StockNumber":null,"StockType":null,"OriginalName":[],"ImageUrl":"https://qccdata.qichacha.com/AutoImage/b402dbcccece51ea9124f8dbc5056761.jpg?x-oss-process=image/resize,w_120","EntType":"0","RecCap":"200万元人民币"},"Status":"200","Message":"查询成功"}