{"OrderNumber":"ECI2019072914424244856151","Result":{"PermissionInfo":[],"Penalty":[],"Exceptions":[],"ShiXinItems":[],"ZhiXingItems":[],"MPledge":[],"Liquidation":null,"Pledge":[],"SpotCheck":[],"CompanyTaxCreditItems":[],"CompanyProducts":[],"PermissionEciInfo":[],"PenaltyCreditChina":[],"Partners":[],"Employees":[],"Branches":[],"ChangeRecords":[{"ProjectName":"负责人变更","BeforeContent":"金喜良","AfterContent":"张寅钦*","ChangeDate":"2018-05-15"}],"ContactInfo":{"WebSite":[{"Name":null,"Url":"www.huachuangmingde.com"}],"PhoneNumber":"021-65050312","Email":"zhangyinqin@huachuangmingde.com"},"Industry":{"IndustryCode":"J","Industry":"金融业","SubIndustryCode":"68","SubIndustry":"保险业","MiddleCategoryCode":"685","MiddleCategory":"保险中介服务","SmallCategoryCode":null,"SmallCategory":null},"Area":{"Province":"上海市","City":"上海市","County":"杨浦区"},"InsuredCount":"10","EnglishName":null,"PersonScope":"","KeyNo":"d621f5474dd59ab33176d9141539eff8","Name":"北京华创明德保险代理有限公司上海分公司","No":"310110000875762","BelongOrg":"杨浦区市场监管局","OperName":"张寅钦","StartDate":"2017-02-16 00:00:00","EndDate":"","Status":"存续（在营、开业、在册）","Province":"SH","UpdatedDate":"2019-07-20 20:19:06","CreditCode":"91310110MA1G8C2R36","RegistCapi":"","EconKind":"有限责任公司分公司（非自然人投资或控股的法人独资）","Address":"上海市杨浦区黄兴路1800号1411室","Scope":"保险专业代理。【依法须经批准的项目,经相关部门批准后方可开展经营活动】","TermStart":"2017-02-16 00:00:00","TeamEnd":"","CheckDate":"2017-02-16 00:00:00","OrgNo":"MA1G8C2R-3","IsOnStock":"0","StockNumber":null,"StockType":null,"OriginalName":[],"ImageUrl":"https://qccdata.qichacha.com/AutoImage/d621f5474dd59ab33176d9141539eff8.jpg?x-oss-process=image/resize,w_120","EntType":"0","RecCap":null},"Status":"200","Message":"查询成功"}