{"OrderNumber":"ECI2019071614122710723533","Result":{"PermissionInfo":[{"Name":"","Province":"北京","Liandate":"2018-10-25","CaseNo":""}],"Penalty":[],"Exceptions":[{"AddReason":"未依照《企业信息公示暂行条例》第八条规定的期限公示年度报告的","AddDate":"2017-07-07","RomoveReason":"列入经营异常名录3年内且依照《经营异常名录管理办法》第六条规定被列入经营异常名录的企业，可以在补报未报年份的年度报告并公示后，申请移出","RemoveDate":"2017-07-17","DecisionOffice":"北京市工商行政管理局","RemoveDecisionOffice":"北京市工商行政管理局"}],"ShiXinItems":[],"ZhiXingItems":[],"MPledge":[],"Liquidation":null,"Pledge":[],"SpotCheck":[],"CompanyTaxCreditItems":[{"No":"911100006851040631","Name":"新光海航人寿保险有限责任公司","Year":"2017","Level":"A"},{"No":"110105685104063","Name":"新光海航人寿保险有限责任公司","Year":"2015","Level":"A"}],"CompanyProducts":[{"CompanyName":"新光海航人寿保险有限责任公司","Link":"http://www.skl-hna.com/","ImageUrl":"http://img.qichacha.com/Product/e1f38a93-619c-433d-8d09-09770efee79a.jpg","Name":"新光海航人寿","Domain":"金融","Tags":"人寿保险,保险,健康保险,意外险,金融","Description":"新光海航人寿是一家保险服务提供商，主营人寿保险、健康保险和意外伤害保险等业务和上述业务的再保险业务，旗下产品包括新光海航金如意C款两全保险、新光海航附加定期重大疾病保险、新光海航新海安意意外伤害保险等。","Category":""}],"PermissionEciInfo":[],"PenaltyCreditChina":[],"Partners":[{"StockName":"新光人寿保险股份有限公司","StockType":"外国(地区)企业","StockPercent":"25.00%","ShouldCapi":"31250","ShoudDate":"2008-05-12","InvestType":"货币","InvestName":null,"RealCapi":null,"CapiDate":null},{"StockName":"深圳市柏霖资产管理有限公司","StockType":"企业法人","StockPercent":"20.00%","ShouldCapi":"25000","ShoudDate":"2018-09-29","InvestType":"货币","InvestName":null,"RealCapi":null,"CapiDate":null},{"StockName":"深圳市前海香江金融控股集团有限公司","StockType":"企业法人","StockPercent":"20.00%","ShouldCapi":"25000","ShoudDate":"2018-09-29","InvestType":"货币","InvestName":null,"RealCapi":null,"CapiDate":null},{"StockName":"深圳市国展投资发展有限公司","StockType":"企业法人","StockPercent":"14.00%","ShouldCapi":"17500","ShoudDate":"2018-09-29","InvestType":"货币","InvestName":null,"RealCapi":null,"CapiDate":null},{"StockName":"深圳市乐安居商业有限公司","StockType":"企业法人","StockPercent":"11.00%","ShouldCapi":"13750","ShoudDate":"2018-09-29","InvestType":"货币","InvestName":null,"RealCapi":null,"CapiDate":null},{"StockName":"上海冠浦房地产开发经营有限公司","StockType":"企业法人","StockPercent":"10.00%","ShouldCapi":"12500","ShoudDate":"2018-09-29","InvestType":"货币","InvestName":null,"RealCapi":null,"CapiDate":null}],"Employees":[{"Name":"万峰","Job":"董事长"},{"Name":"方正培","Job":"总经理,董事"},{"Name":"伍美旭","Job":"董事"},{"Name":"周艳","Job":"董事"},{"Name":"陈伟","Job":"董事"},{"Name":"成小云","Job":"董事"},{"Name":"黄尚夫","Job":"董事"},{"Name":"宗建新","Job":"董事"},{"Name":"张海丹","Job":"监事"},{"Name":"邱立权","Job":"监事"}],"Branches":[{"CompanyId":"136743f1a9347ed864309d4daa2c896a","RegNo":"911101055585164875","Name":"鼎诚人寿保险有限责任公司北京市朝阳支公司","BelongOrg":"北京市工商行政管理局朝阳分局","CreditCode":null,"OperName":null},{"CompanyId":"29d4a7b7a899b233ff8d7684b65edadf","RegNo":"91460100562439576N","Name":"鼎诚人寿保险有限责任公司海南省分公司","BelongOrg":"海口市市场监督管理局","CreditCode":null,"OperName":null},{"CompanyId":"3326665b61ce9fcee291a956eb2e3396","RegNo":"91610000586997038R","Name":"鼎诚人寿保险有限责任公司陕西分公司","BelongOrg":"陕西省工商行政管理局","CreditCode":null,"OperName":null},{"CompanyId":"348c75697efa63c24df63c952daa9afa","RegNo":"91460100090538938U","Name":"鼎诚人寿保险有限责任公司海南省分公司电话销售中心","BelongOrg":"海口市市场监督管理局","CreditCode":null,"OperName":null},{"CompanyId":"8017a06f19aa50e1e4b78677739eb0e7","RegNo":"91320000398297843E","Name":"新光海航人寿保险有限责任公司江苏分公司","BelongOrg":"江苏省市场监督管理局","CreditCode":null,"OperName":null},{"CompanyId":"a79793882c49c251c76aaa4ab6d70835","RegNo":"914601005949210175","Name":"鼎诚人寿保险有限责任公司海南省分公司海口营销服务部","BelongOrg":"海口市市场监督管理局","CreditCode":null,"OperName":null},{"CompanyId":"c1253e48391b430b041ae2fb1adaa7be","RegNo":"91610000MA6TGCJ13E","Name":"新光海航人寿保险有限责任公司陕西分公司电话销售中心","BelongOrg":"陕西省工商行政管理局","CreditCode":null,"OperName":null}],"ChangeRecords":[{"ProjectName":"企业名称","BeforeContent":"新光海航人寿保险有限责任公司","AfterContent":"鼎诚人寿保险有限责任公司","ChangeDate":"2019-06-10"},{"ProjectName":"法定代表人","BeforeContent":"成小云","AfterContent":"万峰*","ChangeDate":"2019-06-10"},{"ProjectName":"注册资本","BeforeContent":"50000","AfterContent":"125000（+150%）","ChangeDate":"2018-10-25"},{"ProjectName":"投资人","BeforeContent":"新光人寿保险股份有限公司,外国(地区)企业；海航集团有限公司,法人股东【退出】","AfterContent":"新光人寿保险股份有限公司,外国(地区)企业；深圳市柏霖资产管理有限公司,企业法人【新增】；深圳市前海香江金融控股集团有限公司,企业法人【新增】；深圳市国展投资发展有限公司,企业法人【新增】；深圳市乐安居商业有限公司,企业法人【新增】；上海冠浦房地产开发经营有限公司,企业法人【新增】","ChangeDate":"2018-10-25"},{"ProjectName":"法定代表人","BeforeContent":"闻安民","AfterContent":"成小云","ChangeDate":"2016-02-05"},{"ProjectName":"住所","BeforeContent":"北京市朝阳区建国路93号万达广场B座写字楼15层","AfterContent":"北京市朝阳区建国门外大街乙12号双子座大厦东塔第6层和第8层","ChangeDate":"2011-06-28"},{"ProjectName":"实收资本（金）","BeforeContent":"0","AfterContent":"50000","ChangeDate":"2009-03-23"},{"ProjectName":"实收资本（金）","BeforeContent":"0 万元","AfterContent":"50000 万元","ChangeDate":"2009-03-23"},{"ProjectName":"董事（理事）、经理、监事","BeforeContent":"闻安民,董事长；潘柏铮,副董事长；邱玉芳,董事；王东辉,董事；蔡雄继,董事【退出】；谭向东,董事；陈日进,独立董事；黄尚夫,独立董事；蔡雄继,总经理【退出】；邱立权,监事；张海丹,监事","AfterContent":"闻安民,董事长；潘柏铮,副董事长；邱玉芳,董事；王东辉,董事；方正培,董事【新增】；谭向东,董事；黄尚夫,独立董事；陈日进,独立董事；方正培,总经理【新增】；邱立权,监事；张海丹,监事","ChangeDate":"2009-11-17"},{"ProjectName":"董事（理事）、经理、监事","BeforeContent":"闻安民,董事长【退出】；潘柏铮,副董事长；方正培,董事；邱玉芳,董事；谭向东,董事；王东辉,董事；黄尚夫,独立董事；陈日进,独立董事；方正培,总经理；邱立权,监事；张海丹,监事","AfterContent":"成小云,董事长【新增】；潘柏铮,副董事长；王东辉,董事；方正培,董事；谭向东,董事；邱玉芳,董事；黄尚夫,独立董事；陈日进,独立董事；方正培,总经理；张海丹,监事；邱立权,监事","ChangeDate":"2016-02-05"},{"ProjectName":"董事（理事）、经理、监事","BeforeContent":"成小云,董事长；潘柏铮,副董事长【退出】；王东辉,董事【退出】；方正培,董事；谭向东,董事【退出】；邱玉芳,董事【退出】；黄尚夫,独立董事；陈日进,独立董事【退出】；方正培,总经理；张海丹,监事；邱立权,监事","AfterContent":"万峰*,董事长【新增】；陈伟,董事【新增】；伍美旭,董事【新增】；周艳,董事【新增】；宗建新,董事【新增】；方正培,董事；黄尚夫,董事；成小云,董事；方正培,总经理；邱立权,监事；张海丹,监事","ChangeDate":"2019-06-10"}],"ContactInfo":{"WebSite":[{"Name":null,"Url":"http://www.skl-hna.com"}],"PhoneNumber":"010-59216666","Email":"meng.liang@skl-hna.com"},"Industry":{"IndustryCode":"J","Industry":"金融业","SubIndustryCode":"68","SubIndustry":"保险业","MiddleCategoryCode":"681","MiddleCategory":"人身保险","SmallCategoryCode":"6811","SmallCategory":"人寿保险"},"Area":{"Province":"北京市","City":"北京市","County":"朝阳区"},"InsuredCount":"66","EnglishName":"Shin Kong-HNA Life Insurance Co., Ltd.","PersonScope":" 100-499人","KeyNo":"5e19dd8339c618652c626c2d692a9fa1","Name":"鼎诚人寿保险有限责任公司","No":"110000450091636","BelongOrg":"北京市工商行政管理局","OperName":"万峰","StartDate":"2009-03-02 00:00:00","EndDate":"","Status":"开业","Province":"BJ","UpdatedDate":"2019-07-15 22:51:16","CreditCode":"911100006851040631","RegistCapi":"125000万元人民币","EconKind":"有限责任公司(台港澳与境内合资)","Address":"北京市朝阳区建国门外大街乙12号双子座大厦东塔第6层和第8层","Scope":"在北京市行政辖区内及已设立分公司的省、自治区、直辖市内经营下列业务(法定保险业务除外):(一)人寿保险、健康保险和意外伤害保险等保险业务;(二)上述业务的再保险业务。(依法须经批准的项目,经相关部门批准后依批准的内容开展经营活动。)","TermStart":"2009-03-02 00:00:00","TeamEnd":"","CheckDate":"2019-06-10 00:00:00","OrgNo":"68510406-3","IsOnStock":"0","StockNumber":null,"StockType":null,"OriginalName":[{"Name":"新光海航人寿保险有限责任公司","ChangeDate":"2019-06-10"}],"ImageUrl":"https://co-image.qichacha.com/CompanyImage/5e19dd8339c618652c626c2d692a9fa1.jpg?x-oss-process=image/resize,w_160","EntType":"0","RecCap":"50000万元人民币"},"Status":"200","Message":"查询成功"}